deployme/__init__.py
deployme/cli/__init__.py
deployme/cli/cli.py
deployme/cli/helpers.py
deployme/cli/commands/__init__.py
deployme/cli/commands/build.py
deployme/cli/commands/cook.py
deployme/cli/commands/info/__init__.py
deployme/cli/commands/info/about.py
deployme/cli/commands/info/backends_list.py
deployme/cli/commands/info/frameworks_list.py
deployme/cli/commands/info/strategies_list.py
deployme/cli/commands/info/version.py
deployme/cli/commands/tools/__init__.py
deployme/cli/commands/tools/detect_serializer.py
deployme/contrib/__init__.py
deployme/contrib/analyzer.py
deployme/contrib/dockerutils.py
deployme/contrib/entrypoint.py
deployme/contrib/project_builder.py
deployme/contrib/supported.py
deployme/contrib/validator.py
deployme/contrib/actions/__init__.py
deployme/contrib/actions/docker_build.py
deployme/contrib/actions/project_build.py
deployme/cookie/__init__.py
deployme/cookie/cutter.py
deployme/cookie/validator.py
deployme/cookie/templates/__init__.py
deployme/cookie/templates/backends/__init__.py
deployme/cookie/templates/backends/dispatcher.py
deployme/cookie/templates/backends/_aiohttp/Dockerfile
deployme/cookie/templates/backends/_aiohttp/__init__.py
deployme/cookie/templates/backends/_aiohttp/requirements.txt
deployme/cookie/templates/backends/_aiohttp/server.py
deployme/cookie/templates/backends/_aiohttp/models/model.pkl
deployme/cookie/templates/backends/_fastapi/Dockerfile
deployme/cookie/templates/backends/_fastapi/__init__.py
deployme/cookie/templates/backends/_fastapi/requirements.txt
deployme/cookie/templates/backends/_fastapi/server.py
deployme/cookie/templates/backends/_fastapi/models/model.pkl
deployme/cookie/templates/backends/_flask/Dockerfile
deployme/cookie/templates/backends/_flask/__init__.py
deployme/cookie/templates/backends/_flask/requirements.txt
deployme/cookie/templates/backends/_flask/server.py
deployme/cookie/templates/backends/_flask/models/model.pkl
deployme/cookie/templates/backends/_sanic/Dockerfile
deployme-0.5.0.dist-info/entry_points.txt
deployme-0.5.0.dist-info/LICENSE
deployme-0.5.0.dist-info/WHEEL
deployme-0.5.0.dist-info/METADATA
deployme-0.5.0.dist-info/RECORD
