Metadata-Version: 2.1
Name: deployme
Version: 0.5.0
Summary: minimalistic ML-models auto deployment tool
Keywords: ML,deploy,AutoDeploy
Author-email: Konstantin Templin <1qnbhd@gmail.com>, Kristina Zheltova <masterkristall@gmail.com>
Maintainer-email: Konstantin Templin <1qnbhd@gmail.com>, Kristina Zheltova <masterkristall@gmail.com>
Requires-Python: >=3.8
Classifier: Intended Audience :: Science/Research
Classifier: Intended Audience :: Developers
Classifier: Programming Language :: Python :: 3
Classifier: Programming Language :: Python :: 3.6
Classifier: Programming Language :: Python :: 3.7
Classifier: Programming Language :: Python :: 3.8
Classifier: Programming Language :: Python :: 3.9
Classifier: Programming Language :: Python :: 3.10
Classifier: Programming Language :: Python :: 3 :: Only
Classifier: Topic :: Scientific/Engineering
Classifier: Topic :: Scientific/Engineering :: Mathematics
Classifier: Topic :: Scientific/Engineering :: Artificial Intelligence
Classifier: Topic :: Software Development
Classifier: Topic :: Software Development :: Libraries
Classifier: Topic :: Software Development :: Libraries :: Python Modules
Requires-Dist: click==8.1.3
Requires-Dist: pandas==1.5.1
Requires-Dist: numpy==1.23.4
Requires-Dist: scikit-learn==1.1.3
Requires-Dist: rich==12.6.0
Requires-Dist: docker==6.0.1
Requires-Dist: importlib_metadata==5.0.0
Requires-Dist: black==22.10.0
Requires-Dist: mypy==0.950
Requires-Dist: returns==0.19.0
Requires-Dist: isort==5.10.1
Requires-Dist: emoji==2.2.0
Requires-Dist: flask==2.2.2
Requires-Dist: pydantic==1.10.2
Requires-Dist: flask-pydantic==0.11.0
Requires-Dist: sanic==22.9.1
Requires-Dist: sanic-ext==22.9.1
Requires-Dist: packaging==21.3
Requires-Dist: nbformat==5.7.0
Requires-Dist: dill==0.3.6
Requires-Dist: joblib==1.2.0
Requires-Dist: tabulate==0.9.0
Project-URL: Repository, https://github.com/qnbhd/deployme
